ShujuKexueSixiangChuyi/README.md
ShujuKexueSixiangChuyi/__init__.py
ShujuKexueSixiangChuyi/__main__.py
ShujuKexueSixiangChuyi/file.epub
ShujuKexueSixiangChuyi/index.html
ShujuKexueSixiangChuyi/css/__init__.py
ShujuKexueSixiangChuyi/css/annotations.css
ShujuKexueSixiangChuyi/css/main.css
ShujuKexueSixiangChuyi/css/normalize.css
ShujuKexueSixiangChuyi/css/popup.css
ShujuKexueSixiangChuyi/font/__init__.py
ShujuKexueSixiangChuyi/font/fontello.eot
ShujuKexueSixiangChuyi/font/fontello.svg
ShujuKexueSixiangChuyi/font/fontello.ttf
ShujuKexueSixiangChuyi/font/fontello.woff
ShujuKexueSixiangChuyi/img/__init__.py
ShujuKexueSixiangChuyi/img/annotator-glyph-sprite.png
ShujuKexueSixiangChuyi/img/annotator-icon-sprite.png
ShujuKexueSixiangChuyi/img/apple-touch-icon.png
ShujuKexueSixiangChuyi/img/cancelfullscreen.png
ShujuKexueSixiangChuyi/img/close.png
ShujuKexueSixiangChuyi/img/fullscreen.png
ShujuKexueSixiangChuyi/img/loader.gif
ShujuKexueSixiangChuyi/img/menu-icon.png
ShujuKexueSixiangChuyi/img/save.png
ShujuKexueSixiangChuyi/img/saved.png
ShujuKexueSixiangChuyi/img/settings-s.png
ShujuKexueSixiangChuyi/img/settings.png
ShujuKexueSixiangChuyi/img/star.png
ShujuKexueSixiangChuyi/js/__init__.py
ShujuKexueSixiangChuyi/js/epub.js
ShujuKexueSixiangChuyi/js/epub.min.js
ShujuKexueSixiangChuyi/js/epub.min.map
ShujuKexueSixiangChuyi/js/hooks.min.js
ShujuKexueSixiangChuyi/js/hooks.min.map
ShujuKexueSixiangChuyi/js/reader.js
ShujuKexueSixiangChuyi/js/reader.js.map
ShujuKexueSixiangChuyi/js/reader.min.js
ShujuKexueSixiangChuyi/js/reader.min.map
ShujuKexueSixiangChuyi/js/hooks/__init__.py
ShujuKexueSixiangChuyi/js/hooks/extensions/__init__.py
ShujuKexueSixiangChuyi/js/hooks/extensions/highlight.js
ShujuKexueSixiangChuyi/js/libs/__init__.py
ShujuKexueSixiangChuyi/js/libs/jquery.min.js
ShujuKexueSixiangChuyi/js/libs/localforage.min.js
ShujuKexueSixiangChuyi/js/libs/screenfull.js
ShujuKexueSixiangChuyi/js/libs/screenfull.min.js
ShujuKexueSixiangChuyi/js/libs/zip.min.js
shuju_kexue_sixiang_chuyi-2024.3.6.0.dist-info/METADATA
shuju_kexue_sixiang_chuyi-2024.3.6.0.dist-info/WHEEL
shuju_kexue_sixiang_chuyi-2024.3.6.0.dist-info/entry_points.txt
shuju_kexue_sixiang_chuyi-2024.3.6.0.dist-info/top_level.txt
shuju_kexue_sixiang_chuyi-2024.3.6.0.dist-info/RECORD
